{
  "meta": {
    "data_version": "1.1.0",
    "created": "2022-03-16",
    "revision": 1
  },
  "info": {
    "balls_per_over": 6,
    "city": "Nottingham",
    "dates": [
      "2015-08-25"
    ],
    "event": {
      "name": "Royal London One-Day Cup",
      "stage": "Quarter Final"
    },
    "gender": "male",
    "match_type": "ODM",
    "missing": [
      {
        "powerplays": {
          "1": [
            "batting"
          ],
          "2": [
            "batting"
          ]
        }
      }
    ],
    "officials": {
      "tv_umpires": [
        "PK Baldwin"
      ],
      "umpires": [
        "JW Lloyds",
        "NA Mallender"
      ]
    },
    "outcome": {
      "winner": "Nottinghamshire",
      "by": {
        "runs": 49
      },
      "method": "D/L"
    },
    "overs": 50,
    "player_of_match": [
      "SR Patel"
    ],
    "players": {
      "Nottinghamshire": [
        "MH Wessels",
        "AD Hales",
        "DT Christian",
        "JWA Taylor",
        "SR Patel",
        "BRM Taylor",
        "SJ Mullaney",
        "CMW Read",
        "BA Hutton",
        "JT Ball",
        "HF Gurney"
      ],
      "Durham": [
        "MD Stoneman",
        "P Mustard",
        "G Clark",
        "PD Collingwood",
        "CS MacLeod",
        "GJ Muchall",
        "RD Pringle",
        "JW Hastings",
        "SG Borthwick",
        "C Rushworth",
        "G Onions"
      ]
    },
    "registry": {
      "people": {
        "AD Hales": "92aeac25",
        "BA Hutton": "b3544c5d",
        "BRM Taylor": "53597be1",
        "C Rushworth": "e737a5fe",
        "CMW Read": "be4cefab",
        "CS MacLeod": "9c376401",
        "DT Christian": "2a2e6343",
        "G Clark": "4fd09cfc",
        "G Onions": "c1f6c27e",
        "GJ Muchall": "a15347c2",
        "HF Gurney": "e412cb64",
        "JT Ball": "3d0ed2f9",
        "JW Hastings": "012829ff",
        "JW Lloyds": "112b8472",
        "JWA Taylor": "c374f37f",
        "MD Stoneman": "1b77f62b",
        "MH Wessels": "90f47cf2",
        "NA Mallender": "3b5dfcd4",
        "P Mustard": "1b6fef02",
        "PD Collingwood": "a386e91b",
        "PK Baldwin": "6bb53c12",
        "RD Pringle": "757502b5",
        "SG Borthwick": "51e1ed69",
        "SJ Mullaney": "0e0d43b4",
        "SR Patel": "18fac429"
      }
    },
    "season": "2015",
    "team_type": "club",
    "teams": [
      "Nottinghamshire",
      "Durham"
    ],
    "toss": {
      "decision": "field",
      "winner": "Durham"
    },
    "venue": "Trent Bridge, Nottingham"
  },
  "innings": [
    {
      "team": "Nottinghamshire",
      "overs": [
        {
          "over": 0,
          "deliveries": [
            {
              "batter": "MH Wessels",
              "bowler": "G Onions",
              "non_striker": "AD Hales",
              "runs": {
                "batter": 0,
                "extras": 0,
                "total": 0
              }
            },
            {
              "batter": "MH Wessels",
              "bowler": "G Onions",
              "non_striker": "AD Hales",
              "runs": {
                "batter": 0,
                "extras": 0,
                "total": 0
              }
            },
            {
              "batter": "MH Wessels",
              "bowler": "G Onions",
              "non_striker": "AD Hales",
              "runs": {
                "batter": 0,
                "extras": 0,
                "total": 0
              }
            },
            {
              "batter": "MH Wessels",
              "bowler": "G Onions",
              "non_striker": "AD Hales",
              "runs": {
                "batter": 0,
                "extras": 0,
                "total": 0
              }
            },
            {
              "batter": "MH Wessels",
              "bowler": "G Onions",
              "non_striker": "AD Hales",
              "runs": {
                "batter": 0,
                "extras": 0,
                "total": 0
              }
            },
            {
              "batter": "MH Wessels",
              "bowler": "G Onions",
              "non_striker": "AD Hales",
              "runs": {
                "batter": 4,
                "extras": 0,
                "total": 4
              }
            }
          ]
        },
        {
          "over": 1,
          "deliveries": [
            {
              "batter": "AD Hales",
              "bowler": "C Rushworth",
              "non_striker": "MH Wessels",
              "runs": {
                "batter": 4,
                "extras": 0,
                "total": 4
              }
            },
            {
              "batter": "AD Hales",
              "bowler": "C Rushworth",
              "non_striker": "MH Wessels",
              "runs": {
                "batter": 4,
                "extras": 0,
                "total": 4
              }
            },
            {
              "batter": "AD Hales",
              "bowler": "C Rushworth",
              "non_striker": "MH Wessels",
              "runs": {
                "batter": 0,
                "extras": 0,
                "total": 0
              }
            },
            {
              "batter": "AD Hales",
              "bowler": "C Rushworth",
              "non_striker": "MH Wessels",
              "runs": {
                "batter": 0,
                "extras": 0,
                "total": 0
              }
            },
            {
              "batter": "AD Hales",
              "bowler": "C Rushworth",
              "non_striker": "MH Wessels",
              "runs": {
                "batter": 0,
                "extras": 0,
                "total": 0
              }
            },
            {
              "batter": "AD Hales",
              "bowler": "C Rushworth",
              "non_striker": "MH Wessels",
              "runs": {
                "batter": 0,
                "extras": 0,
                "total": 0
              }
            }
          ]
        },
        {
          "over": 2,
          "deliveries": [
            {
              "batter": "MH Wessels",
              "bowler": "G Onions",
              "non_striker": "AD Hales",
              "runs": {
                "batter": 1,
                "extras": 0,
                "total": 1
              }
            },
            {
              "batter": "AD Hales",
              "bowler": "G Onions",
              "non_striker": "MH Wessels",
              "runs": {
                "batter": 0,
                "extras": 0,
                "total": 0
              }
            },
            {
              "batter": "AD Hales",
              "bowler": "G Onions",
              "non_striker": "MH Wessels",
              "runs": {
                "batter": 1,
                "extras": 0,
                "total": 1
              }
            },
            {
              "batter": "MH Wessels",
              "bowler": "G Onions",
              "non_striker": "AD Hales",
              "runs": {
                "batter": 1,
                "extras": 0,
                "total": 1
              }
            },
            {
              "batter": "AD Hales",
              "bowler": "G Onions",
              "non_striker": "MH Wessels",
              "runs": {
                "batter": 0,
                "extras": 0,
                "total": 0
              }
            },
            {
              "batter": "AD Hales",
              "bowler": "G Onions",
              "non_striker": "MH Wessels",
              "runs": {
                "batter": 4,
                "extras": 0,
                "total": 4
              }
            }
          ]
        },
        {
          "over": 3,
          "deliveries": [
            {
              "batter": "MH Wessels",
              "bowler": "C Rushworth",
              "non_striker": "AD Hales",
              "runs": {
                "batter": 0,
                "extras": 0,
                "total": 0
              }
            },
            {
              "batter": "MH Wessels",
              "bowler": "C Rushworth",
              "extras": {
                "legbyes": 1
              },
              "non_striker": "AD Hales",
              "runs": {
                "batter": 0,
                "extras": 1,
                "total": 1
              }
            },
            {
              "batter": "AD Hales",
              "bowler": "C Rushworth",
              "non_striker": "MH Wessels",
              "runs": {
                "batter": 0,
                "extras": 0,
                "total": 0
              }
            },
            {
              "batter": "AD Hales",
              "bowler": "C Rushworth",
              "non_striker": "MH Wessels",
              "runs": {
                "batter": 0,
                "extras": 0,
                "total": 0
              }
            },
            {
              "batter": "AD Hales",
              "bowler": "C Rushworth",
              "non_striker": "MH Wessels",
              "runs": {
                "batter": 0,
                "extras": 0,
                "total": 0
              }
            },
            {
              "batter": "AD Hales",
              "bowler": "C Rushworth",
              "non_striker": "MH Wessels",
              "runs": {
                "batter": 0,
                "extras": 0,
                "total": 0
              }
            }
          ]
        },
        {
          "over": 4,
          "deliveries": [
            {
              "batter": "MH Wessels",
              "bowler": "G Onions",
              "non_striker": "AD Hales",
              "runs": {
                "batter": 0,
                "extras": 0,
                "total": 0
              }
            },
            {
              "batter": "MH Wessels",
              "bowler": "G Onions",
              "non_striker": "AD Hales",
              "runs": {
                "batter": 0,
                "extras": 0,
                "total": 0
              }
            },
            {
              "batter": "MH Wessels",
              "bowler": "G Onions",
              "non_striker": "AD Hales",
              "runs": {
                "batter": 0,
                "extras": 0,
                "total": 0
              }
            },
            {
              "batter": "MH Wessels",
              "bowler": "G Onions",
              "non_striker": "AD Hales",
              "runs": {
                "batter": 0,
                "extras": 0,
                "total": 0
              }
            },
            {
              "batter": "MH Wessels",
              "bowler": "G Onions",
              "non_striker": "AD Hales",
              "runs": {
                "batter": 2,
                "extras": 0,
                "total": 2
              }
            },
            {
              "batter": "MH Wessels",
              "bowler": "G Onions",
              "non_striker": "AD Hales",
              "runs": {
                "batter": 0,
                "extras": 0,
                "total": 0
              }
            }
          ]
        },
        {
          "over": 5,
          "deliveries": [
            {
              "batter": "AD Hales",
              "bowler": "C Rushworth",
              "non_striker": "MH Wessels",
              "runs": {
                "batter": 4,
                "extras": 0,
                "total": 4
              }
            },
            {
              "batter": "AD Hales",
              "bowler": "C Rushworth",
              "non_striker": "MH Wessels",
              "runs": {
                "batter": 0,
                "extras": 0,
                "total": 0
              }
            },
            {
              "batter": "AD Hales",
              "bowler": "C Rushworth",
              "non_striker": "MH Wessels",
              "runs": {
                "batter": 3,
                "extras": 0,
                "total": 3
              }
            },
            {
              "batter": "MH Wessels",
              "bowler": "C Rushworth",
              "non_striker": "AD Hales",
              "runs": {
                "batter": 0,
                "extras": 0,
                "total": 0
              }
            },
            {
              "batter": "MH Wessels",
              "bowler": "C Rushworth",
              "non_striker": "AD Hales",
              "runs": {
                "batter": 0,
                "extras": 0,
                "total": 0
              }
            },
            {
              "batter": "MH Wessels",
              "bowler": "C Rushworth",
              "non_striker": "AD Hales",
              "runs": {
                "batter": 1,
                "extras": 0,
                "total": 1
              }
            }
          ]
        },
        {
          "over": 6,
          "deliveries": [
            {
              "batter": "MH Wessels",
              "bowler": "G Onions",
              "non_striker": "AD Hales",
              "runs": {
                "batter": 4,
                "extras": 0,
                "total": 4
              }
            },
            {
              "batter": "MH Wessels",
              "bowler": "G Onions",
              "non_striker": "AD Hales",
              "runs": {
                "batter": 0,
                "extras": 0,
                "total": 0
              }
            },
            {
              "batter": "MH Wessels",
              "bowler": "G Onions",
              "non_striker": "AD Hales",
              "runs": {
                "batter": 0,
                "extras": 0,
                "total": 0
              }
            },
            {
              "batter": "MH Wessels",
              "bowler": "G Onions",
              "non_striker": "AD Hales",
              "runs": {
                "batter": 1,
                "extras": 0,
                "total": 1
              }
            },
            {
              "batter": "AD Hales",
              "bowler": "G Onions",
              "non_striker": "MH Wessels",
              "runs": {
                "batter": 0,
                "extras": 0,
                "total": 0
              }
            },
            {
              "batter": "AD Hales",
              "bowler": "G Onions",
              "non_striker": "MH Wessels",
              "runs": {
                "batter": 1,
                "extras": 0,
                "total": 1
              }
            }
          ]
        },
        {
          "over": 7,
          "deliveries": [
            {
              "batter": "AD Hales",
              "bowler": "C Rushworth",
              "non_striker": "MH Wessels",
              "runs": {
                "batter": 0,
                "extras": 0,
                "total": 0
              }
            },
            {
              "batter": "AD Hales",
              "bowler": "C Rushworth",
              "non_striker": "MH Wessels",
              "runs": {
                "batter": 0,
                "extras": 0,
                "total": 0
              }
            },
            {
              "batter": "AD Hales",
              "bowler": "C Rushworth",
              "non_striker": "MH Wessels",
              "runs": {
                "batter": 4,
                "extras": 0,
                "total": 4
              }
            },
            {
              "batter": "AD Hales",
              "bowler": "C Rushworth",
              "non_striker": "MH Wessels",
              "runs": {
                "batter": 0,
                "extras": 0,
                "total": 0
              }
            },
            {
              "batter": "AD Hales",
              "bowler": "C Rushworth",
              "non_striker": "MH Wessels",
              "runs": {
                "batter": 0,
                "extras": 0,
                "total": 0
              }
            },
            {
              "batter": "AD Hales",
              "bowler": "C Rushworth",
              "non_striker": "MH Wessels",
              "runs": {
                "batter": 0,
                "extras": 0,
                "total": 0
              }
            }
          ]
        },
        {
          "over": 8,
          "deliveries": [
            {
              "batter": "MH Wessels",
              "bowler": "G Onions",
              "non_striker": "AD Hales",
              "runs": {
                "batter": 0,
                "extras": 0,
                "total": 0
              }
            },
            {
              "batter": "MH Wessels",
              "bowler": "G Onions",
              "non_striker": "AD Hales",
              "runs": {
                "batter": 1,
                "extras": 0,
                "total": 1
              }
            },
            {
              "batter": "AD Hales",
              "bowler": "G Onions",
              "non_striker": "MH Wessels",
              "runs": {
                "batter": 0,
                "extras": 0,
                "total": 0
              }
            },
            {
              "batter": "AD Hales",
              "bowler": "G Onions",
              "non_striker": "MH Wessels",
              "runs": {
                "batter": 0,
                "extras": 0,
                "total": 0
              }
            },
            {
              "batter": "AD Hales",
              "bowler": "G Onions",
              "non_striker": "MH Wessels",
              "runs": {
                "batter": 1,
                "extras": 0,
                "total": 1
              }
            },
            {
              "batter": "MH Wessels",
              "bowler": "G Onions",
              "non_striker": "AD Hales",
              "runs": {
                "batter": 4,
                "extras": 0,
                "total": 4
              }
            }
          ]
        },
        {
          "over": 9,
          "deliveries": [
            {
              "batter": "AD Hales",
              "bowler": "JW Hastings",
              "non_striker": "MH Wessels",
              "runs": {
                "batter": 0,
                "extras": 0,
                "total": 0
              }
            },
            {
              "batter": "AD Hales",
              "bowler": "JW Hastings",
              "non_striker": "MH Wessels",
              "runs": {
                "batter": 1,
                "extras": 0,
                "total": 1
              }
            },
            {
              "batter": "MH Wessels",
              "bowler": "JW Hastings",
              "non_striker": "AD Hales",
              "runs": {
                "batter": 0,
                "extras": 0,
                "total": 0
              }
            },
            {
              "batter": "MH Wessels",
              "bowler": "JW Hastings",
              "non_striker": "AD Hales",
              "runs": {
                "batter": 0,
                "extras": 0,
                "total": 0
              }
            },
            {
              "batter": "MH Wessels",
              "bowler": "JW Hastings",
              "non_striker": "AD Hales",
              "runs": {
                "batter": 1,
                "extras": 0,
                "total": 1
              }
            },
            {
              "batter": "AD Hales",
              "bowler": "JW Hastings",
              "non_striker": "MH Wessels",
              "runs": {
                "batter": 0,
                "extras": 0,
                "total": 0
              }
            }
          ]
        },
        {
          "over": 10,
          "deliveries": [
            {
              "batter": "MH Wessels",
              "bowler": "G Onions",
              "non_striker": "AD Hales",
              "runs": {
                "batter": 0,
                "extras": 0,
                "total": 0
              }
            },
            {
              "batter": "MH Wessels",
              "bowler": "G Onions",
              "non_striker": "AD Hales",
              "runs": {
                "batter": 0,
                "extras": 0,
                "total": 0
              }
            },
            {
              "batter": "MH Wessels",
              "bowler": "G Onions",
              "non_striker": "AD Hales",
              "runs": {
                "batter": 0,
                "extras": 0,
                "total": 0
              }
            },
            {
              "batter": "MH Wessels",
              "bowler": "G Onions",
              "non_striker": "AD Hales",
              "runs": {
                "batter": 4,
                "extras": 0,
                "total": 4
              }
            },
            {
              "batter": "MH Wessels",
              "bowler": "G Onions",
              "non_striker": "AD Hales",
              "runs": {
                "batter": 0,
                "extras": 0,
                "total": 0
              }
            },
            {
              "batter": "MH Wessels",
              "bowler": "G Onions",
              "non_striker": "AD Hales",
              "runs": {
                "batter": 0,
                "extras": 0,
                "total": 0
              }
            }
          ]
        },
        {
          "over": 11,
          "deliveries": [
            {
              "batter": "AD Hales",
              "bowler": "JW Hastings",
              "non_striker": "MH Wessels",
              "runs": {
                "batter": 1,
                "extras": 0,
                "total": 1
              }
            },
            {
              "batter": "MH Wessels",
              "bowler": "JW Hastings",
              "non_striker": "AD Hales",
              "runs": {
                "batter": 0,
                "extras": 0,
                "total": 0
              }
            },
            {
              "batter": "MH Wessels",
              "bowler": "JW Hastings",
              "non_striker": "AD Hales",
              "runs": {
                "batter": 1,
                "extras": 0,
                "total": 1
              }
            },
            {
              "batter": "AD Hales",
              "bowler": "JW Hastings",
              "non_striker": "MH Wessels",
              "runs": {
                "batter": 1,
                "extras": 0,
                "total": 1
              }
            },
            {
              "batter": "MH Wessels",
              "bowler": "JW Hastings",
              "non_striker": "AD Hales",
              "runs": {
                "batter": 0,
                "extras": 0,
                "total": 0
              }
            },
            {
              "batter": "MH Wessels",
              "bowler": "JW Hastings",
              "non_striker": "AD Hales",
              "runs": {
                "batter": 0,
                "extras": 0,
                "total": 0
              },
              "wickets": [
                {
                  "player_out": "MH Wessels",
                  "fielders": [
                    {
                      "name": "SG Borthwick"
                    }
                  ],
                  "kind": "caught"
                }
              ]
            }
          ]
        },
        {
          "over": 12,
          "deliveries": [
            {
              "batter": "AD Hales",
              "bowler": "G Onions",
              "non_striker": "DT Christian",
              "runs": {
                "batter": 1,
                "extras": 0,
                "total": 1
              }
            },
            {
              "batter": "DT Christian",
              "bowler": "G Onions",
              "non_striker": "AD Hales",
              "runs": {
                "batter": 4,
                "extras": 0,
                "total": 4
              }
            },
            {
              "batter": "DT Christian",
              "bowler": "G Onions",
              "non_striker": "AD Hales",
              "runs": {
                "batter": 0,
                "extras": 0,
                "total": 0
              }
            },
            {
              "batter": "DT Christian",
              "bowler": "G Onions",
              "non_striker": "AD Hales",
              "runs": {
                "batter": 0,
                "extras": 0,
                "total": 0
              }
            },
            {
              "batter": "DT Christian",
              "bowler": "G Onions",
              "non_striker": "AD Hales",
              "runs": {
                "batter": 0,
                "extras": 0,
                "total": 0
              }
            },
            {
              "batter": "DT Christian",
              "bowler": "G Onions",
              "non_striker": "AD Hales",
              "runs": {
                "batter": 0,
                "extras": 0,
                "total": 0
              }
            }
          ]
        },
        {
          "over": 13,
          "deliveries": [
            {
              "batter": "AD Hales",
              "bowler": "JW Hastings",
              "non_striker": "DT Christian",
              "runs": {
                "batter": 2,
                "extras": 0,
                "total": 2
              }
            },
            {
              "batter": "AD Hales",
              "bowler": "JW Hastings",
              "non_striker": "DT Christian",
              "runs": {
                "batter": 0,
                "extras": 0,
                "total": 0
              }
            },
            {
              "batter": "AD Hales",
              "bowler": "JW Hastings",
              "non_striker": "DT Christian",
              "runs": {
                "batter": 1,
                "extras": 0,
                "total": 1
              }
            },
            {
              "batter": "DT Christian",
              "bowler": "JW Hastings",
              "non_striker": "AD Hales",
              "runs": {
                "batter": 1,
                "extras": 0,
                "total": 1
              }
            },
            {
              "batter": "AD Hales",
              "bowler": "JW Hastings",
              "non_striker": "DT Christian",
              "runs": {
                "batter": 0,
                "extras": 0,
                "total": 0
              }
            },
            {
              "batter": "AD Hales",
              "bowler": "JW Hastings",
              "non_striker": "DT Christian",
              "runs": {
                "batter": 1,
                "extras": 0,
                "total": 1
              }
            }
          ]
        },
        {
          "over": 14,
          "deliveries": [
            {
              "batter": "AD Hales",
              "bowler": "G Onions",
              "non_striker": "DT Christian",
              "runs": {
                "batter": 0,
                "extras": 0,
                "total": 0
              }
            },
            {
              "batter": "AD Hales",
              "bowler": "G Onions",
              "non_striker": "DT Christian",
              "runs": {
                "batter": 1,
                "extras": 0,
                "total": 1
              }
            },
            {
              "batter": "DT Christian",
              "bowler": "G Onions",
              "non_striker": "AD Hales",
              "runs": {
                "batter": 0,
                "extras": 0,
                "total": 0
              }
            },
            {
              "batter": "DT Christian",
              "bowler": "G Onions",
              "non_striker": "AD Hales",
              "runs": {
                "batter": 4,
                "extras": 0,
                "total": 4
              }
            },
            {
              "batter": "DT Christian",
              "bowler": "G Onions",
              "non_striker": "AD Hales",
              "runs": {
                "batter": 1,
                "extras": 0,
                "total": 1
              }
            },
            {
              "batter": "AD Hales",
              "bowler": "G Onions",
              "non_striker": "DT Christian",
              "runs": {
                "batter": 4,
                "extras": 0,
                "total": 4
              }
            }
          ]
        },
        {
          "over": 15,
          "deliveries": [
            {
              "batter": "DT Christian",
              "bowler": "JW Hastings",
              "non_striker": "AD Hales",
              "runs": {
                "batter": 1,
                "extras": 0,
                "total": 1
              }
            },
            {
              "batter": "AD Hales",
              "bowler": "JW Hastings",
              "non_striker": "DT Christian",
              "runs": {
                "batter": 1,
                "extras": 0,
                "total": 1
              }
            },
            {
              "batter": "DT Christian",
              "bowler": "JW Hastings",
              "non_striker": "AD Hales",
              "runs": {
                "batter": 0,
                "extras": 0,
                "total": 0
              }
            },
            {
              "batter": "DT Christian",
              "bowler": "JW Hastings",
              "non_striker": "AD Hales",
              "runs": {
                "batter": 1,
                "extras": 0,
                "total": 1
              }
            },
            {
              "batter": "AD Hales",
              "bowler": "JW Hastings",
              "non_striker": "DT Christian",
              "runs": {
                "batter": 0,
                "extras": 0,
                "total": 0
              }
            },
            {
              "batter": "AD Hales",
              "bowler": "JW Hastings",
              "non_striker": "DT Christian",
              "runs": {
                "batter": 4,
                "extras": 0,
                "total": 4
              }
            }
          ]
        },
        {
          "over": 16,
          "deliveries": [
            {
              "batter": "DT Christian",
              "bowler": "SG Borthwick",
              "non_striker": "AD Hales",
              "runs": {
                "batter": 0,
                "extras": 0,
                "total": 0
              }
            },
            {
              "batter": "DT Christian",
              "bowler": "SG Borthwick",
              "non_striker": "AD Hales",
              "runs": {
                "batter": 1,
                "extras": 0,
                "total": 1
              }
            },
            {
              "batter": "AD Hales",
              "bowler": "SG Borthwick",
              "non_striker": "DT Christian",
              "runs": {
                "batter": 6,
                "extras": 0,
                "total": 6
              }
            },
            {
              "batter": "AD Hales",
              "bowler": "SG Borthwick",
              "non_striker": "DT Christian",
              "runs": {
                "batter": 1,
                "extras": 0,
                "total": 1
              }
            },
            {
              "batter": "DT Christian",
              "bowler": "SG Borthwick",
              "non_striker": "AD Hales",
              "runs": {
                "batter": 1,
                "extras": 0,
                "total": 1
              }
            },
            {
              "batter": "AD Hales",
              "bowler": "SG Borthwick",
              "non_striker": "DT Christian",
              "runs": {
                "batter": 2,
                "extras": 0,
                "total": 2
              }
            }
          ]
        },
        {
          "over": 17,
          "deliveries": [
            {
              "batter": "DT Christian",
              "bowler": "JW Hastings",
              "non_striker": "AD Hales",
              "runs": {
                "batter": 1,
                "extras": 0,
                "total": 1
              }
            },
            {
              "batter": "AD Hales",
              "bowler": "JW Hastings",
              "non_striker": "DT Christian",
              "runs": {
                "batter": 0,
                "extras": 0,
                "total": 0
              }
            },
            {
              "batter": "AD Hales",
              "bowler": "JW Hastings",
              "non_striker": "DT Christian",
              "runs": {
                "batter": 1,
                "extras": 0,
                "total": 1
              }
            },
            {
              "batter": "DT Christian",
              "bowler": "JW Hastings",
              "non_striker": "AD Hales",
              "runs": {
                "batter": 0,
                "extras": 0,
                "total": 0
              }
            },
            {
              "batter": "DT Christian",
              "bowler": "JW Hastings",
              "non_striker": "AD Hales",
              "runs": {
                "batter": 2,
                "extras": 0,
                "total": 2
              }
            },
            {
              "batter": "DT Christian",
              "bowler": "JW Hastings",
              "non_striker": "AD Hales",
              "runs": {
                "batter": 4,
                "extras": 0,
                "total": 4
              }
            }
          ]
        },
        {
          "over": 18,
          "deliveries": [
            {
              "batter": "AD Hales",
              "bowler": "PD Collingwood",
              "non_striker": "DT Christian",
              "runs": {
                "batter": 0,
                "extras": 0,
                "total": 0
              }
            },
            {
              "batter": "AD Hales",
              "bowler": "PD Collingwood",
              "non_striker": "DT Christian",
              "runs": {
                "batter": 2,
                "extras": 0,
                "total": 2
              }
            },
            {
              "batter": "AD Hales",
              "bowler": "PD Collingwood",
              "non_striker": "DT Christian",
              "runs": {
                "batter": 6,
                "extras": 0,
                "total": 6
              }
            },
            {
              "batter": "AD Hales",
              "bowler": "PD Collingwood",
              "non_striker": "DT Christian",
              "runs": {
                "batter": 0,
                "extras": 0,
                "total": 0
              },
              "wickets": [
                {
                  "player_out": "AD Hales",
                  "fielders": [
                    {
                      "name": "RD Pringle"
                    }
                  ],
                  "kind": "caught"
                }
              ]
            },
            {
              "batter": "DT Christian",
              "bowler": "PD Collingwood",
              "non_striker": "JWA Taylor",
              "runs": {
                "batter": 1,
                "extras": 0,
                "total": 1
              }
            },
            {
              "batter": "JWA Taylor",
              "bowler": "PD Collingwood",
              "non_striker": "DT Christian",
              "runs": {
                "batter": 0,
                "extras": 0,
                "total": 0
              }
            }
          ]
        },
        {
          "over": 19,
          "deliveries": [
            {
              "batter": "DT Christian",
              "bowler": "SG Borthwick",
              "non_striker": "JWA Taylor",
              "runs": {
                "batter": 0,
                "extras": 0,
                "total": 0
              }
            },
            {
              "batter": "DT Christian",
              "bowler": "SG Borthwick",
              "non_striker": "JWA Taylor",
              "runs": {
                "batter": 1,
                "extras": 0,
                "total": 1
              }
            },
            {
              "batter": "JWA Taylor",
              "bowler": "SG Borthwick",
              "non_striker": "DT Christian",
              "runs": {
                "batter": 1,
                "extras": 0,
                "total": 1
              }
            },
            {
              "batter": "DT Christian",
              "bowler": "SG Borthwick",
              "non_striker": "JWA Taylor",
              "runs": {
                "batter": 0,
                "extras": 0,
                "total": 0
              }
            },
            {
              "batter": "DT Christian",
              "bowler": "SG Borthwick",
              "non_striker": "JWA Taylor",
              "runs": {
                "batter": 6,
                "extras": 0,
                "total": 6
              }
            },
            {
              "batter": "DT Christian",
              "bowler": "SG Borthwick",
              "non_striker": "JWA Taylor",
              "runs": {
                "batter": 1,
                "extras": 0,
                "total": 1
              }
            }
          ]
        },
        {
          "over": 20,
          "deliveries": [
            {
              "batter": "DT Christian",
              "bowler": "PD Collingwood",
              "non_striker": "JWA Taylor",
              "runs": {
                "batter": 2,
                "extras": 0,
                "total": 2
              }
            },
            {
              "batter": "DT Christian",
              "bowler": "PD Collingwood",
              "non_striker": "JWA Taylor",
              "runs": {
                "batter": 6,
                "extras": 0,
                "total": 6
              }
            },
            {
              "batter": "DT Christian",
              "bowler": "PD Collingwood",
              "non_striker": "JWA Taylor",
              "runs": {
                "batter": 1,
                "extras": 0,
                "total": 1
              }
            },
            {
              "batter": "JWA Taylor",
              "bowler": "PD Collingwood",
              "extras": {
                "legbyes": 1
              },
              "non_striker": "DT Christian",
              "runs": {
                "batter": 0,
                "extras": 1,
                "total": 1
              }
            },
            {
              "batter": "DT Christian",
              "bowler": "PD Collingwood",
              "non_striker": "JWA Taylor",
              "runs": {
                "batter": 2,
                "extras": 0,
                "total": 2
              }
            },
            {
              "batter": "DT Christian",
              "bowler": "PD Collingwood",
              "non_striker": "JWA Taylor",
              "runs": {
                "batter": 2,
                "extras": 0,
                "total": 2
              }
            }
          ]
        },
        {
          "over": 21,
          "deliveries": [
            {
              "batter": "JWA Taylor",
              "bowler": "SG Borthwick",
              "non_striker": "DT Christian",
              "runs": {
                "batter": 1,
                "extras": 0,
                "total": 1
              }
            },
            {
              "batter": "DT Christian",
              "bowler": "SG Borthwick",
              "non_striker": "JWA Taylor",
              "runs": {
                "batter": 1,
                "extras": 0,
                "total": 1
              }
            },
            {
              "batter": "JWA Taylor",
              "bowler": "SG Borthwick",
              "non_striker": "DT Christian",
              "runs": {
                "batter": 6,
                "extras": 0,
                "total": 6
              }
            },
            {
              "batter": "JWA Taylor",
              "bowler": "SG Borthwick",
              "non_striker": "DT Christian",
              "runs": {
                "batter": 6,
                "extras": 0,
                "total": 6
              }
            },
            {
              "batter": "JWA Taylor",
              "bowler": "SG Borthwick",
              "non_striker": "DT Christian",
              "runs": {
                "batter": 6,
                "extras": 0,
                "total": 6
              }
            },
            {
              "batter": "JWA Taylor",
              "bowler": "SG Borthwick",
              "non_striker": "DT Christian",
              "runs": {
                "batter": 1,
                "extras": 0,
                "total": 1
              }
            }
          ]
        },
        {
          "over": 22,
          "deliveries": [
            {
              "batter": "JWA Taylor",
              "bowler": "C Rushworth",
              "non_striker": "DT Christian",
              "runs": {
                "batter": 0,
                "extras": 0,
                "total": 0
              }
            },
            {
              "batter": "JWA Taylor",
              "bowler": "C Rushworth",
              "non_striker": "DT Christian",
              "runs": {
                "batter": 1,
                "extras": 0,
                "total": 1
              }
            },
            {
              "batter": "DT Christian",
              "bowler": "C Rushworth",
              "non_striker": "JWA Taylor",
              "runs": {
                "batter": 1,
                "extras": 0,
                "total": 1
              }
            },
            {
              "batter": "JWA Taylor",
              "bowler": "C Rushworth",
              "extras": {
                "noballs": 2
              },
              "non_striker": "DT Christian",
              "runs": {
                "batter": 4,
                "extras": 2,
                "total": 6
              }
            },
            {
              "batter": "JWA Taylor",
              "bowler": "C Rushworth",
              "non_striker": "DT Christian",
              "runs": {
                "batter": 0,
                "extras": 0,
                "total": 0
              }
            },
            {
              "batter": "JWA Taylor",
              "bowler": "C Rushworth",
              "non_striker": "DT Christian",
              "runs": {
                "batter": 2,
                "extras": 0,
                "total": 2
              }
            },
            {
              "batter": "JWA Taylor",
              "bowler": "C Rushworth",
              "non_striker": "DT Christian",
              "runs": {
                "batter": 1,
                "extras": 0,
                "total": 1
              }
            }
          ]
        },
        {
          "over": 23,
          "deliveries": [
            {
              "batter": "JWA Taylor",
              "bowler": "PD Collingwood",
              "non_striker": "DT Christian",
              "runs": {
                "batter": 0,
                "extras": 0,
                "total": 0
              },
              "wickets": [
                {
                  "player_out": "JWA Taylor",
                  "fielders": [
                    {
                      "name": "G Onions"
                    }
                  ],
                  "kind": "caught"
                }
              ]
            },
            {
              "batter": "DT Christian",
              "bowler": "PD Collingwood",
              "non_striker": "SR Patel",
              "runs": {
                "batter": 1,
                "extras": 0,
                "total": 1
              }
            },
            {
              "batter": "SR Patel",
              "bowler": "PD Collingwood",
              "non_striker": "DT Christian",
              "runs": {
                "batter": 1,
                "extras": 0,
                "total": 1
              }
            },
            {
              "batter": "DT Christian",
              "bowler": "PD Collingwood",
              "non_striker": "SR Patel",
              "runs": {
                "batter": 2,
                "extras": 0,
                "total": 2
              }
            },
            {
              "batter": "DT Christian",
              "bowler": "PD Collingwood",
              "extras": {
                "legbyes": 1
              },
              "non_striker": "SR Patel",
              "runs": {
                "batter": 0,
                "extras": 1,
                "total": 1
              }
            },
            {
              "batter": "SR Patel",
              "bowler": "PD Collingwood",
              "non_striker": "DT Christian",
              "runs": {
                "batter": 0,
                "extras": 0,
                "total": 0
              },
              "wickets": [
                {
                  "player_out": "SR Patel",
                  "fielders": [
                    {
                      "name": "C Rushworth"
                    }
                  ],
                  "kind": "caught"
                }
              ]
            }
          ]
        }
      ],
      "powerplays": [
        {
          "from": 0.1,
          "to": 9.6,
          "type": "mandatory"
        }
      ]
    },
    {
      "team": "Durham",
      "overs": [
        {
          "over": 0,
          "deliveries": [
            {
              "batter": "MD Stoneman",
              "bowler": "HF Gurney",
              "extras": {
                "wides": 2
              },
              "non_striker": "P Mustard",
              "runs": {
                "batter": 0,
                "extras": 2,
                "total": 2
              }
            },
            {
              "batter": "P Mustard",
              "bowler": "HF Gurney",
              "non_striker": "MD Stoneman",
              "runs": {
                "batter": 4,
                "extras": 0,
                "total": 4
              }
            },
            {
              "batter": "P Mustard",
              "bowler": "HF Gurney",
              "non_striker": "MD Stoneman",
              "runs": {
                "batter": 1,
                "extras": 0,
                "total": 1
              }
            },
            {
              "batter": "MD Stoneman",
              "bowler": "HF Gurney",
              "non_striker": "P Mustard",
              "runs": {
                "batter": 0,
                "extras": 0,
                "total": 0
              }
            },
            {
              "batter": "MD Stoneman",
              "bowler": "HF Gurney",
              "non_striker": "P Mustard",
              "runs": {
                "batter": 4,
                "extras": 0,
                "total": 4
              }
            },
            {
              "batter": "MD Stoneman",
              "bowler": "HF Gurney",
              "non_striker": "P Mustard",
              "runs": {
                "batter": 1,
                "extras": 0,
                "total": 1
              }
            },
            {
              "batter": "P Mustard",
              "bowler": "HF Gurney",
              "non_striker": "MD Stoneman",
              "runs": {
                "batter": 0,
                "extras": 0,
                "total": 0
              }
            }
          ]
        },
        {
          "over": 1,
          "deliveries": [
            {
              "batter": "MD Stoneman",
              "bowler": "BA Hutton",
              "non_striker": "P Mustard",
              "runs": {
                "batter": 4,
                "extras": 0,
                "total": 4
              }
            },
            {
              "batter": "MD Stoneman",
              "bowler": "BA Hutton",
              "non_striker": "P Mustard",
              "runs": {
                "batter": 1,
                "extras": 0,
                "total": 1
              }
            },
            {
              "batter": "P Mustard",
              "bowler": "BA Hutton",
              "extras": {
                "legbyes": 1
              },
              "non_striker": "MD Stoneman",
              "runs": {
                "batter": 0,
                "extras": 1,
                "total": 1
              }
            },
            {
              "batter": "MD Stoneman",
              "bowler": "BA Hutton",
              "non_striker": "P Mustard",
              "runs": {
                "batter": 0,
                "extras": 0,
                "total": 0
              }
            },
            {
              "batter": "MD Stoneman",
              "bowler": "BA Hutton",
              "non_striker": "P Mustard",
              "runs": {
                "batter": 0,
                "extras": 0,
                "total": 0
              }
            },
            {
              "batter": "MD Stoneman",
              "bowler": "BA Hutton",
              "non_striker": "P Mustard",
              "runs": {
                "batter": 4,
                "extras": 0,
                "total": 4
              }
            }
          ]
        },
        {
          "over": 2,
          "deliveries": [
            {
              "batter": "P Mustard",
              "bowler": "HF Gurney",
              "non_striker": "MD Stoneman",
              "runs": {
                "batter": 0,
                "extras": 0,
                "total": 0
              }
            },
            {
              "batter": "P Mustard",
              "bowler": "HF Gurney",
              "non_striker": "MD Stoneman",
              "runs": {
                "batter": 0,
                "extras": 0,
                "total": 0
              }
            },
            {
              "batter": "P Mustard",
              "bowler": "HF Gurney",
              "non_striker": "MD Stoneman",
              "runs": {
                "batter": 0,
                "extras": 0,
                "total": 0
              }
            },
            {
              "batter": "P Mustard",
              "bowler": "HF Gurney",
              "non_striker": "MD Stoneman",
              "runs": {
                "batter": 0,
                "extras": 0,
                "total": 0
              }
            },
            {
              "batter": "P Mustard",
              "bowler": "HF Gurney",
              "non_striker": "MD Stoneman",
              "runs": {
                "batter": 0,
                "extras": 0,
                "total": 0
              }
            },
            {
              "batter": "P Mustard",
              "bowler": "HF Gurney",
              "non_striker": "MD Stoneman",
              "runs": {
                "batter": 1,
                "extras": 0,
                "total": 1
              }
            }
          ]
        },
        {
          "over": 3,
          "deliveries": [
            {
              "batter": "P Mustard",
              "bowler": "JT Ball",
              "non_striker": "MD Stoneman",
              "runs": {
                "batter": 0,
                "extras": 0,
                "total": 0
              }
            },
            {
              "batter": "P Mustard",
              "bowler": "JT Ball",
              "non_striker": "MD Stoneman",
              "runs": {
                "batter": 1,
                "extras": 0,
                "total": 1
              }
            },
            {
              "batter": "MD Stoneman",
              "bowler": "JT Ball",
              "non_striker": "P Mustard",
              "runs": {
                "batter": 0,
                "extras": 0,
                "total": 0
              }
            },
            {
              "batter": "MD Stoneman",
              "bowler": "JT Ball",
              "non_striker": "P Mustard",
              "runs": {
                "batter": 4,
                "extras": 0,
                "total": 4
              }
            },
            {
              "batter": "MD Stoneman",
              "bowler": "JT Ball",
              "non_striker": "P Mustard",
              "runs": {
                "batter": 1,
                "extras": 0,
                "total": 1
              }
            },
            {
              "batter": "P Mustard",
              "bowler": "JT Ball",
              "non_striker": "MD Stoneman",
              "runs": {
                "batter": 4,
                "extras": 0,
                "total": 4
              }
            }
          ]
        },
        {
          "over": 4,
          "deliveries": [
            {
              "batter": "MD Stoneman",
              "bowler": "HF Gurney",
              "non_striker": "P Mustard",
              "runs": {
                "batter": 1,
                "extras": 0,
                "total": 1
              }
            },
            {
              "batter": "P Mustard",
              "bowler": "HF Gurney",
              "non_striker": "MD Stoneman",
              "runs": {
                "batter": 0,
                "extras": 0,
                "total": 0
              }
            },
            {
              "batter": "P Mustard",
              "bowler": "HF Gurney",
              "non_striker": "MD Stoneman",
              "runs": {
                "batter": 4,
                "extras": 0,
                "total": 4
              }
            },
            {
              "batter": "P Mustard",
              "bowler": "HF Gurney",
              "non_striker": "MD Stoneman",
              "runs": {
                "batter": 4,
                "extras": 0,
                "total": 4
              }
            },
            {
              "batter": "P Mustard",
              "bowler": "HF Gurney",
              "non_striker": "MD Stoneman",
              "runs": {
                "batter": 0,
                "extras": 0,
                "total": 0
              }
            },
            {
              "batter": "P Mustard",
              "bowler": "HF Gurney",
              "non_striker": "MD Stoneman",
              "runs": {
                "batter": 0,
                "extras": 0,
                "total": 0
              }
            }
          ]
        },
        {
          "over": 5,
          "deliveries": [
            {
              "batter": "MD Stoneman",
              "bowler": "JT Ball",
              "non_striker": "P Mustard",
              "runs": {
                "batter": 0,
                "extras": 0,
                "total": 0
              }
            },
            {
              "batter": "MD Stoneman",
              "bowler": "JT Ball",
              "non_striker": "P Mustard",
              "runs": {
                "batter": 0,
                "extras": 0,
                "total": 0
              }
            },
            {
              "batter": "MD Stoneman",
              "bowler": "JT Ball",
              "non_striker": "P Mustard",
              "runs": {
                "batter": 0,
                "extras": 0,
                "total": 0
              }
            },
            {
              "batter": "MD Stoneman",
              "bowler": "JT Ball",
              "non_striker": "P Mustard",
              "runs": {
                "batter": 6,
                "extras": 0,
                "total": 6
              }
            },
            {
              "batter": "MD Stoneman",
              "bowler": "JT Ball",
              "non_striker": "P Mustard",
              "runs": {
                "batter": 4,
                "extras": 0,
                "total": 4
              }
            },
            {
              "batter": "MD Stoneman",
              "bowler": "JT Ball",
              "non_striker": "P Mustard",
              "runs": {
                "batter": 0,
                "extras": 0,
                "total": 0
              }
            }
          ]
        },
        {
          "over": 6,
          "deliveries": [
            {
              "batter": "P Mustard",
              "bowler": "DT Christian",
              "non_striker": "MD Stoneman",
              "runs": {
                "batter": 4,
                "extras": 0,
                "total": 4
              }
            },
            {
              "batter": "P Mustard",
              "bowler": "DT Christian",
              "non_striker": "MD Stoneman",
              "runs": {
                "batter": 1,
                "extras": 0,
                "total": 1
              }
            },
            {
              "batter": "MD Stoneman",
              "bowler": "DT Christian",
              "non_striker": "P Mustard",
              "runs": {
                "batter": 4,
                "extras": 0,
                "total": 4
              }
            },
            {
              "batter": "MD Stoneman",
              "bowler": "DT Christian",
              "non_striker": "P Mustard",
              "runs": {
                "batter": 0,
                "extras": 0,
                "total": 0
              }
            },
            {
              "batter": "MD Stoneman",
              "bowler": "DT Christian",
              "non_striker": "P Mustard",
              "runs": {
                "batter": 2,
                "extras": 0,
                "total": 2
              }
            },
            {
              "batter": "MD Stoneman",
              "bowler": "DT Christian",
              "non_striker": "P Mustard",
              "runs": {
                "batter": 0,
                "extras": 0,
                "total": 0
              },
              "wickets": [
                {
                  "player_out": "MD Stoneman",
                  "fielders": [
                    {
                      "name": "BA Hutton"
                    }
                  ],
                  "kind": "caught"
                }
              ]
            }
          ]
        },
        {
          "over": 7,
          "deliveries": [
            {
              "batter": "P Mustard",
              "bowler": "SJ Mullaney",
              "non_striker": "G Clark",
              "runs": {
                "batter": 0,
                "extras": 0,
                "total": 0
              }
            },
            {
              "batter": "P Mustard",
              "bowler": "SJ Mullaney",
              "non_striker": "G Clark",
              "runs": {
                "batter": 0,
                "extras": 0,
                "total": 0
              }
            },
            {
              "batter": "P Mustard",
              "bowler": "SJ Mullaney",
              "non_striker": "G Clark",
              "runs": {
                "batter": 0,
                "extras": 0,
                "total": 0
              },
              "wickets": [
                {
                  "player_out": "P Mustard",
                  "fielders": [
                    {
                      "name": "MH Wessels"
                    }
                  ],
                  "kind": "caught"
                }
              ]
            },
            {
              "batter": "G Clark",
              "bowler": "SJ Mullaney",
              "non_striker": "PD Collingwood",
              "runs": {
                "batter": 1,
                "extras": 0,
                "total": 1
              }
            },
            {
              "batter": "PD Collingwood",
              "bowler": "SJ Mullaney",
              "non_striker": "G Clark",
              "runs": {
                "batter": 0,
                "extras": 0,
                "total": 0
              },
              "wickets": [
                {
                  "player_out": "PD Collingwood",
                  "kind": "caught and bowled"
                }
              ]
            },
            {
              "batter": "CS MacLeod",
              "bowler": "SJ Mullaney",
              "non_striker": "G Clark",
              "runs": {
                "batter": 1,
                "extras": 0,
                "total": 1
              }
            }
          ]
        },
        {
          "over": 8,
          "deliveries": [
            {
              "batter": "CS MacLeod",
              "bowler": "BA Hutton",
              "non_striker": "G Clark",
              "runs": {
                "batter": 1,
                "extras": 0,
                "total": 1
              }
            },
            {
              "batter": "G Clark",
              "bowler": "BA Hutton",
              "non_striker": "CS MacLeod",
              "runs": {
                "batter": 0,
                "extras": 0,
                "total": 0
              }
            },
            {
              "batter": "G Clark",
              "bowler": "BA Hutton",
              "non_striker": "CS MacLeod",
              "runs": {
                "batter": 0,
                "extras": 0,
                "total": 0
              }
            },
            {
              "batter": "G Clark",
              "bowler": "BA Hutton",
              "extras": {
                "wides": 1
              },
              "non_striker": "CS MacLeod",
              "runs": {
                "batter": 0,
                "extras": 1,
                "total": 1
              }
            },
            {
              "batter": "G Clark",
              "bowler": "BA Hutton",
              "non_striker": "CS MacLeod",
              "runs": {
                "batter": 1,
                "extras": 0,
                "total": 1
              }
            },
            {
              "batter": "CS MacLeod",
              "bowler": "BA Hutton",
              "non_striker": "G Clark",
              "runs": {
                "batter": 0,
                "extras": 0,
                "total": 0
              }
            },
            {
              "batter": "CS MacLeod",
              "bowler": "BA Hutton",
              "extras": {
                "wides": 1
              },
              "non_striker": "G Clark",
              "runs": {
                "batter": 0,
                "extras": 1,
                "total": 1
              }
            },
            {
              "batter": "CS MacLeod",
              "bowler": "BA Hutton",
              "non_striker": "G Clark",
              "runs": {
                "batter": 1,
                "extras": 0,
                "total": 1
              }
            }
          ]
        },
        {
          "over": 9,
          "deliveries": [
            {
              "batter": "CS MacLeod",
              "bowler": "SJ Mullaney",
              "non_striker": "G Clark",
              "runs": {
                "batter": 4,
                "extras": 0,
                "total": 4
              }
            },
            {
              "batter": "CS MacLeod",
              "bowler": "SJ Mullaney",
              "non_striker": "G Clark",
              "runs": {
                "batter": 4,
                "extras": 0,
                "total": 4
              }
            },
            {
              "batter": "CS MacLeod",
              "bowler": "SJ Mullaney",
              "non_striker": "G Clark",
              "runs": {
                "batter": 0,
                "extras": 0,
                "total": 0
              }
            },
            {
              "batter": "CS MacLeod",
              "bowler": "SJ Mullaney",
              "non_striker": "G Clark",
              "runs": {
                "batter": 1,
                "extras": 0,
                "total": 1
              }
            },
            {
              "batter": "G Clark",
              "bowler": "SJ Mullaney",
              "non_striker": "CS MacLeod",
              "runs": {
                "batter": 0,
                "extras": 0,
                "total": 0
              }
            },
            {
              "batter": "G Clark",
              "bowler": "SJ Mullaney",
              "non_striker": "CS MacLeod",
              "runs": {
                "batter": 0,
                "extras": 0,
                "total": 0
              }
            }
          ]
        },
        {
          "over": 10,
          "deliveries": [
            {
              "batter": "CS MacLeod",
              "bowler": "BA Hutton",
              "non_striker": "G Clark",
              "runs": {
                "batter": 1,
                "extras": 0,
                "total": 1
              }
            },
            {
              "batter": "G Clark",
              "bowler": "BA Hutton",
              "non_striker": "CS MacLeod",
              "runs": {
                "batter": 0,
                "extras": 0,
                "total": 0
              }
            },
            {
              "batter": "G Clark",
              "bowler": "BA Hutton",
              "non_striker": "CS MacLeod",
              "runs": {
                "batter": 0,
                "extras": 0,
                "total": 0
              }
            },
            {
              "batter": "G Clark",
              "bowler": "BA Hutton",
              "non_striker": "CS MacLeod",
              "runs": {
                "batter": 1,
                "extras": 0,
                "total": 1
              }
            },
            {
              "batter": "CS MacLeod",
              "bowler": "BA Hutton",
              "non_striker": "G Clark",
              "runs": {
                "batter": 0,
                "extras": 0,
                "total": 0
              }
            },
            {
              "batter": "CS MacLeod",
              "bowler": "BA Hutton",
              "non_striker": "G Clark",
              "runs": {
                "batter": 0,
                "extras": 0,
                "total": 0
              }
            }
          ]
        },
        {
          "over": 11,
          "deliveries": [
            {
              "batter": "G Clark",
              "bowler": "SJ Mullaney",
              "non_striker": "CS MacLeod",
              "runs": {
                "batter": 0,
                "extras": 0,
                "total": 0
              }
            },
            {
              "batter": "G Clark",
              "bowler": "SJ Mullaney",
              "non_striker": "CS MacLeod",
              "runs": {
                "batter": 1,
                "extras": 0,
                "total": 1
              }
            },
            {
              "batter": "CS MacLeod",
              "bowler": "SJ Mullaney",
              "non_striker": "G Clark",
              "runs": {
                "batter": 0,
                "extras": 0,
                "total": 0
              }
            },
            {
              "batter": "CS MacLeod",
              "bowler": "SJ Mullaney",
              "non_striker": "G Clark",
              "runs": {
                "batter": 2,
                "extras": 0,
                "total": 2
              }
            },
            {
              "batter": "CS MacLeod",
              "bowler": "SJ Mullaney",
              "non_striker": "G Clark",
              "runs": {
                "batter": 1,
                "extras": 0,
                "total": 1
              }
            },
            {
              "batter": "G Clark",
              "bowler": "SJ Mullaney",
              "non_striker": "CS MacLeod",
              "runs": {
                "batter": 0,
                "extras": 0,
                "total": 0
              }
            }
          ]
        },
        {
          "over": 12,
          "deliveries": [
            {
              "batter": "CS MacLeod",
              "bowler": "BA Hutton",
              "non_striker": "G Clark",
              "runs": {
                "batter": 1,
                "extras": 0,
                "total": 1
              }
            },
            {
              "batter": "G Clark",
              "bowler": "BA Hutton",
              "non_striker": "CS MacLeod",
              "runs": {
                "batter": 0,
                "extras": 0,
                "total": 0
              }
            },
            {
              "batter": "G Clark",
              "bowler": "BA Hutton",
              "non_striker": "CS MacLeod",
              "runs": {
                "batter": 2,
                "extras": 0,
                "total": 2
              }
            },
            {
              "batter": "G Clark",
              "bowler": "BA Hutton",
              "non_striker": "CS MacLeod",
              "runs": {
                "batter": 6,
                "extras": 0,
                "total": 6
              }
            },
            {
              "batter": "G Clark",
              "bowler": "BA Hutton",
              "non_striker": "CS MacLeod",
              "runs": {
                "batter": 0,
                "extras": 0,
                "total": 0
              }
            },
            {
              "batter": "G Clark",
              "bowler": "BA Hutton",
              "non_striker": "CS MacLeod",
              "runs": {
                "batter": 0,
                "extras": 0,
                "total": 0
              }
            }
          ]
        },
        {
          "over": 13,
          "deliveries": [
            {
              "batter": "CS MacLeod",
              "bowler": "SJ Mullaney",
              "non_striker": "G Clark",
              "runs": {
                "batter": 4,
                "extras": 0,
                "total": 4
              }
            },
            {
              "batter": "CS MacLeod",
              "bowler": "SJ Mullaney",
              "non_striker": "G Clark",
              "runs": {
                "batter": 2,
                "extras": 0,
                "total": 2
              }
            },
            {
              "batter": "CS MacLeod",
              "bowler": "SJ Mullaney",
              "non_striker": "G Clark",
              "runs": {
                "batter": 2,
                "extras": 0,
                "total": 2
              }
            },
            {
              "batter": "CS MacLeod",
              "bowler": "SJ Mullaney",
              "non_striker": "G Clark",
              "runs": {
                "batter": 1,
                "extras": 0,
                "total": 1
              }
            },
            {
              "batter": "G Clark",
              "bowler": "SJ Mullaney",
              "non_striker": "CS MacLeod",
              "runs": {
                "batter": 1,
                "extras": 0,
                "total": 1
              }
            },
            {
              "batter": "CS MacLeod",
              "bowler": "SJ Mullaney",
              "non_striker": "G Clark",
              "runs": {
                "batter": 4,
                "extras": 0,
                "total": 4
              }
            }
          ]
        },
        {
          "over": 14,
          "deliveries": [
            {
              "batter": "G Clark",
              "bowler": "DT Christian",
              "non_striker": "CS MacLeod",
              "runs": {
                "batter": 4,
                "extras": 0,
                "total": 4
              }
            },
            {
              "batter": "G Clark",
              "bowler": "DT Christian",
              "non_striker": "CS MacLeod",
              "runs": {
                "batter": 1,
                "extras": 0,
                "total": 1
              }
            },
            {
              "batter": "CS MacLeod",
              "bowler": "DT Christian",
              "non_striker": "G Clark",
              "runs": {
                "batter": 1,
                "extras": 0,
                "total": 1
              }
            },
            {
              "batter": "G Clark",
              "bowler": "DT Christian",
              "non_striker": "CS MacLeod",
              "runs": {
                "batter": 6,
                "extras": 0,
                "total": 6
              }
            },
            {
              "batter": "G Clark",
              "bowler": "DT Christian",
              "non_striker": "CS MacLeod",
              "runs": {
                "batter": 0,
                "extras": 0,
                "total": 0
              }
            },
            {
              "batter": "G Clark",
              "bowler": "DT Christian",
              "non_striker": "CS MacLeod",
              "runs": {
                "batter": 1,
                "extras": 0,
                "total": 1
              }
            }
          ]
        },
        {
          "over": 15,
          "deliveries": [
            {
              "batter": "G Clark",
              "bowler": "SR Patel",
              "non_striker": "CS MacLeod",
              "runs": {
                "batter": 2,
                "extras": 0,
                "total": 2
              }
            },
            {
              "batter": "G Clark",
              "bowler": "SR Patel",
              "non_striker": "CS MacLeod",
              "runs": {
                "batter": 1,
                "extras": 0,
                "total": 1
              }
            },
            {
              "batter": "CS MacLeod",
              "bowler": "SR Patel",
              "non_striker": "G Clark",
              "runs": {
                "batter": 1,
                "extras": 0,
                "total": 1
              }
            },
            {
              "batter": "G Clark",
              "bowler": "SR Patel",
              "non_striker": "CS MacLeod",
              "runs": {
                "batter": 0,
                "extras": 0,
                "total": 0
              },
              "wickets": [
                {
                  "player_out": "G Clark",
                  "fielders": [
                    {
                      "name": "JWA Taylor"
                    }
                  ],
                  "kind": "caught"
                }
              ]
            },
            {
              "batter": "GJ Muchall",
              "bowler": "SR Patel",
              "non_striker": "CS MacLeod",
              "runs": {
                "batter": 0,
                "extras": 0,
                "total": 0
              }
            },
            {
              "batter": "GJ Muchall",
              "bowler": "SR Patel",
              "non_striker": "CS MacLeod",
              "runs": {
                "batter": 1,
                "extras": 0,
                "total": 1
              }
            }
          ]
        },
        {
          "over": 16,
          "deliveries": [
            {
              "batter": "GJ Muchall",
              "bowler": "JT Ball",
              "non_striker": "CS MacLeod",
              "runs": {
                "batter": 1,
                "extras": 0,
                "total": 1
              }
            },
            {
              "batter": "CS MacLeod",
              "bowler": "JT Ball",
              "non_striker": "GJ Muchall",
              "runs": {
                "batter": 1,
                "extras": 0,
                "total": 1
              }
            },
            {
              "batter": "GJ Muchall",
              "bowler": "JT Ball",
              "non_striker": "CS MacLeod",
              "runs": {
                "batter": 1,
                "extras": 0,
                "total": 1
              }
            },
            {
              "batter": "CS MacLeod",
              "bowler": "JT Ball",
              "non_striker": "GJ Muchall",
              "runs": {
                "batter": 0,
                "extras": 0,
                "total": 0
              }
            },
            {
              "batter": "CS MacLeod",
              "bowler": "JT Ball",
              "non_striker": "GJ Muchall",
              "runs": {
                "batter": 1,
                "extras": 0,
                "total": 1
              }
            },
            {
              "batter": "GJ Muchall",
              "bowler": "JT Ball",
              "non_striker": "CS MacLeod",
              "runs": {
                "batter": 1,
                "extras": 0,
                "total": 1
              }
            }
          ]
        },
        {
          "over": 17,
          "deliveries": [
            {
              "batter": "GJ Muchall",
              "bowler": "SR Patel",
              "non_striker": "CS MacLeod",
              "runs": {
                "batter": 0,
                "extras": 0,
                "total": 0
              }
            },
            {
              "batter": "GJ Muchall",
              "bowler": "SR Patel",
              "non_striker": "CS MacLeod",
              "runs": {
                "batter": 0,
                "extras": 0,
                "total": 0
              }
            },
            {
              "batter": "GJ Muchall",
              "bowler": "SR Patel",
              "non_striker": "CS MacLeod",
              "runs": {
                "batter": 1,
                "extras": 0,
                "total": 1
              }
            },
            {
              "batter": "CS MacLeod",
              "bowler": "SR Patel",
              "non_striker": "GJ Muchall",
              "runs": {
                "batter": 0,
                "extras": 0,
                "total": 0
              },
              "wickets": [
                {
                  "player_out": "CS MacLeod",
                  "fielders": [
                    {
                      "name": "AD Hales"
                    }
                  ],
                  "kind": "caught"
                }
              ]
            },
            {
              "batter": "RD Pringle",
              "bowler": "SR Patel",
              "non_striker": "GJ Muchall",
              "runs": {
                "batter": 1,
                "extras": 0,
                "total": 1
              }
            },
            {
              "batter": "GJ Muchall",
              "bowler": "SR Patel",
              "non_striker": "RD Pringle",
              "runs": {
                "batter": 0,
                "extras": 0,
                "total": 0
              }
            }
          ]
        },
        {
          "over": 18,
          "deliveries": [
            {
              "batter": "RD Pringle",
              "bowler": "SJ Mullaney",
              "non_striker": "GJ Muchall",
              "runs": {
                "batter": 0,
                "extras": 0,
                "total": 0
              }
            },
            {
              "batter": "RD Pringle",
              "bowler": "SJ Mullaney",
              "non_striker": "GJ Muchall",
              "runs": {
                "batter": 1,
                "extras": 0,
                "total": 1
              }
            },
            {
              "batter": "GJ Muchall",
              "bowler": "SJ Mullaney",
              "non_striker": "RD Pringle",
              "runs": {
                "batter": 0,
                "extras": 0,
                "total": 0
              },
              "wickets": [
                {
                  "player_out": "GJ Muchall",
                  "fielders": [
                    {
                      "name": "SR Patel"
                    }
                  ],
                  "kind": "caught"
                }
              ]
            },
            {
              "batter": "JW Hastings",
              "bowler": "SJ Mullaney",
              "non_striker": "RD Pringle",
              "runs": {
                "batter": 0,
                "extras": 0,
                "total": 0
              }
            },
            {
              "batter": "JW Hastings",
              "bowler": "SJ Mullaney",
              "non_striker": "RD Pringle",
              "runs": {
                "batter": 1,
                "extras": 0,
                "total": 1
              }
            },
            {
              "batter": "RD Pringle",
              "bowler": "SJ Mullaney",
              "non_striker": "JW Hastings",
              "runs": {
                "batter": 1,
                "extras": 0,
                "total": 1
              }
            }
          ]
        },
        {
          "over": 19,
          "deliveries": [
            {
              "batter": "RD Pringle",
              "bowler": "SR Patel",
              "non_striker": "JW Hastings",
              "runs": {
                "batter": 0,
                "extras": 0,
                "total": 0
              },
              "wickets": [
                {
                  "player_out": "RD Pringle",
                  "fielders": [
                    {
                      "name": "AD Hales"
                    }
                  ],
                  "kind": "caught"
                }
              ]
            },
            {
              "batter": "JW Hastings",
              "bowler": "SR Patel",
              "non_striker": "SG Borthwick",
              "runs": {
                "batter": 1,
                "extras": 0,
                "total": 1
              }
            },
            {
              "batter": "SG Borthwick",
              "bowler": "SR Patel",
              "non_striker": "JW Hastings",
              "runs": {
                "batter": 2,
                "extras": 0,
                "total": 2
              }
            },
            {
              "batter": "SG Borthwick",
              "bowler": "SR Patel",
              "non_striker": "JW Hastings",
              "runs": {
                "batter": 1,
                "extras": 0,
                "total": 1
              }
            },
            {
              "batter": "JW Hastings",
              "bowler": "SR Patel",
              "non_striker": "SG Borthwick",
              "runs": {
                "batter": 0,
                "extras": 0,
                "total": 0
              },
              "wickets": [
                {
                  "player_out": "JW Hastings",
                  "fielders": [
                    {
                      "name": "DT Christian"
                    }
                  ],
                  "kind": "caught"
                }
              ]
            },
            {
              "batter": "C Rushworth",
              "bowler": "SR Patel",
              "non_striker": "SG Borthwick",
              "runs": {
                "batter": 0,
                "extras": 0,
                "total": 0
              }
            }
          ]
        },
        {
          "over": 20,
          "deliveries": [
            {
              "batter": "SG Borthwick",
              "bowler": "HF Gurney",
              "non_striker": "C Rushworth",
              "runs": {
                "batter": 0,
                "extras": 0,
                "total": 0
              }
            },
            {
              "batter": "SG Borthwick",
              "bowler": "HF Gurney",
              "non_striker": "C Rushworth",
              "runs": {
                "batter": 1,
                "extras": 0,
                "total": 1
              }
            },
            {
              "batter": "C Rushworth",
              "bowler": "HF Gurney",
              "non_striker": "SG Borthwick",
              "runs": {
                "batter": 1,
                "extras": 0,
                "total": 1
              }
            },
            {
              "batter": "SG Borthwick",
              "bowler": "HF Gurney",
              "non_striker": "C Rushworth",
              "runs": {
                "batter": 1,
                "extras": 0,
                "total": 1
              },
              "wickets": [
                {
                  "player_out": "C Rushworth",
                  "fielders": [
                    {
                      "name": "SJ Mullaney"
                    }
                  ],
                  "kind": "run out"
                }
              ]
            },
            {
              "batter": "SG Borthwick",
              "bowler": "HF Gurney",
              "non_striker": "G Onions",
              "runs": {
                "batter": 0,
                "extras": 0,
                "total": 0
              }
            },
            {
              "batter": "SG Borthwick",
              "bowler": "HF Gurney",
              "non_striker": "G Onions",
              "runs": {
                "batter": 1,
                "extras": 0,
                "total": 1
              }
            }
          ]
        },
        {
          "over": 21,
          "deliveries": [
            {
              "batter": "SG Borthwick",
              "bowler": "JT Ball",
              "non_striker": "G Onions",
              "runs": {
                "batter": 0,
                "extras": 0,
                "total": 0
              }
            },
            {
              "batter": "SG Borthwick",
              "bowler": "JT Ball",
              "non_striker": "G Onions",
              "runs": {
                "batter": 0,
                "extras": 0,
                "total": 0
              },
              "wickets": [
                {
                  "player_out": "SG Borthwick",
                  "kind": "bowled"
                }
              ]
            }
          ]
        }
      ],
      "powerplays": [
        {
          "from": 0.1,
          "to": 4.6,
          "type": "mandatory"
        }
      ],
      "target": {
        "overs": 24,
        "runs": 194
      }
    }
  ]
}